[
    [
        {"stroke": [0, 0, 0]},
        {"strokeWidth": 1},
        {"line": [479, -155, 475, -139]},
        {"line": [475, -139, 476, -130]},
        {"line": [476, -130, 479, -117]},
        {"line": [479, -117, 479, -104]},
        {"line": [479, -104, 477, -94]},
        {"line": [477, -94, 476, -69]},
        {"line": [476, -69, 479, -46]},
        {"bezier": [479, -46, 479, -45, 479, -40, 479, -40]},
        {"line": [479, -40, 478, -25]},
        {"line": [478, -25, 479, -14]},
        {"bezier": [479, -14, 478, -11, 473, -11, 473, -11]},
        {"line": [473, -11, 467, -12]},
        {"line": [467, -12, 463, -10]},
        {"line": [463, -10, 459, -11]},
        {"line": [459, -11, 452, -11]},
        {"line": [452, -11, 449, -9]},
        {"bezier": [449, -9, 448, -9, 445, -11, 445, -11]},
        {"line": [445, -11, 441, -13]},
        {"line": [441, -13, 440, -17]},
        {"line": [440, -17, 443, -20]},
        {"line": [443, -20, 449, -23]},
        {"line": [449, -23, 452, -27]},
        {"line": [452, -27, 458, -37]},
        {"line": [458, -37, 457, -39]},
        {"line": [457, -39, 456, -57]},
        {"line": [456, -57, 454, -64]},
        {"line": [454, -64, 448, -80]},
        {"line": [448, -80, 442, -93]},
        {"line": [442, -93, 442, -100]},
        {"line": [442, -100, 441, -109]},
        {"bezier": [441, -109, 436, -119, 444, -160, 444, -160]},
        {"line": [444, -160, 443, -185]},
        {"bezier": [443, -185, 440, -189, 434, -214, 434, -214]},
        {"bezier": [434, -214, 429, -220, 427, -254, 427, -254]},
        {"bezier": [427, -254, 423, -261, 423, -286, 423, -286]},
        {"line": [423, -286, 426, -292]},
        {"bezier": [426, -292, 425, -301, 432, -327, 432, -327]},
        {"bezier": [432, -327, 430, -331, 432, -347, 432, -347]},
        {"line": [432, -347, 434, -358]},
        {"bezier": [434, -358, 432, -360, 424, -380, 424, -380]},
        {"line": [424, -380, 422, -369]},
        {"line": [422, -369, 423, -353]},
        {"line": [423, -353, 417, -324]},
        {"line": [417, -324, 405, -297]},
        {"line": [405, -297, 402, -283]},
        {"line": [402, -283, 405, -280]},
        {"bezier": [405, -280, 408, -276, 407, -269, 407, -269]},
        {"line": [407, -269, 413, -259]},
        {"line": [413, -259, 414, -250]},
        {"line": [414, -250, 409, -249]},
        {"line": [409, -249, 406, -251]},
        {"line": [406, -251, 404, -257]},
        {"line": [404, -257, 402, -261]},
        {"line": [402, -261, 400, -262]},
        {"line": [400, -262, 399, -260]},
        {"line": [399, -260, 400, -253]},
        {"line": [400, -253, 401, -248]},
        {"line": [401, -248, 403, -245]},
        {"bezier": [403, -245, 403, -245, 406, -244, 408, -242]},
        {"bezier": [408, -242, 410, -240, 409, -236, 409, -236]},
        {"line": [409, -236, 406, -235]},
        {"bezier": [406, -235, 407, -233, 405, -233, 405, -233]},
        {"bezier": [405, -233, 395, -231, 388, -244, 388, -244]},
        {"bezier": [388, -244, 383, -256, 385, -264, 385, -264]},
        {"bezier": [385, -264, 385, -264, 387, -296, 387, -295]},
        {"bezier": [387, -295, 386, -295, 389, -326, 389, -326]},
        {"bezier": [389, -326, 386, -343, 398, -376, 398, -376]},
        {"line": [398, -376, 396, -394]},
        {"bezier": [396, -394, 395, -399, 397, -407, 397, -407]},
        {"bezier": [397, -407, 393, -411, 394, -421, 394, -421]},
        {"bezier": [394, -421, 393, -428, 406, -447, 406, -447]},
        {"line": [406, -447, 411, -448]},
        {"line": [411, -448, 415, -453]},
        {"line": [415, -453, 451, -468]},
        {"line": [451, -468, 453, -470]},
        {"line": [453, -470, 458, -475]},
        {"bezier": [458, -475, 459, -477, 458, -490, 458, -490]},
        {"line": [458, -490, 457, -498]},
        {"line": [457, -498, 455, -498]},
        {"line": [455, -498, 448, -507]},
        {"bezier": [448, -507, 448, -507, 448, -519, 448, -520]},
        {"line": [448, -520, 452, -522]},
        {"bezier": [452, -522, 450, -524, 453, -535, 453, -535]},
        {"bezier": [453, -535, 455, -541, 469, -551, 469, -551]},
        {"line": [469, -551, 472, -551]},
        {"line": [472, -551, 493, -551]},
        {"bezier": [493, -551, 506, -541, 508, -535, 508, -535]},
        {"bezier": [508, -535, 512, -523, 509, -522, 509, -522]},
        {"line": [509, -522, 513, -520]},
        {"line": [513, -520, 514, -507]},
        {"line": [514, -507, 507, -498]},
        {"line": [507, -498, 505, -498]},
        {"line": [505, -498, 503, -475]},
        {"line": [503, -475, 511, -468]},
        {"line": [511, -468, 545, -452]},
        {"line": [545, -452, 550, -448]},
        {"line": [550, -448, 555, -446]},
        {"bezier": [555, -446, 565, -431, 566, -422, 566, -422]},
        {"bezier": [566, -422, 568, -415, 564, -407, 564, -407]},
        {"bezier": [564, -407, 566, -401, 564, -393, 564, -393]},
        {"line": [564, -393, 562, -376]},
        {"bezier": [562, -376, 573, -346, 571, -326, 571, -326]},
        {"line": [571, -326, 573, -295]},
        {"line": [573, -295, 574, -263]},
        {"bezier": [574, -263, 576, -253, 572, -243, 572, -243]},
        {"bezier": [572, -243, 559, -224, 554, -234, 554, -234]},
        {"line": [554, -234, 551, -235]},
        {"bezier": [551, -235, 549, -237, 552, -242, 552, -242]},
        {"line": [552, -242, 557, -244]},
        {"line": [557, -244, 560, -248]},
        {"line": [560, -248, 560, -252]},
        {"line": [560, -252, 561, -259]},
        {"line": [561, -259, 560, -261]},
        {"line": [560, -261, 558, -260]},
        {"line": [558, -260, 554, -250]},
        {"line": [554, -250, 551, -248]},
        {"line": [551, -248, 546, -249]},
        {"line": [546, -249, 547, -258]},
        {"line": [547, -258, 553, -269]},
        {"bezier": [553, -269, 550, -278, 558, -282, 558, -282]},
        {"line": [558, -282, 555, -296]},
        {"line": [555, -296, 543, -323]},
        {"line": [543, -323, 538, -351]},
        {"line": [538, -351, 538, -369]},
        {"line": [538, -369, 536, -381]},
        {"line": [536, -381, 527, -357]},
        {"bezier": [527, -357, 532, -340, 529, -326, 529, -326]},
        {"bezier": [529, -326, 536, -303, 535, -291, 535, -291]},
        {"line": [535, -291, 538, -285]},
        {"bezier": [538, -285, 537, -256, 534, -253, 534, -253]},
        {"bezier": [534, -253, 531, -219, 526, -213, 526, -213]},
        {"line": [526, -213, 518, -184]},
        {"line": [518, -184, 517, -159]},
        {"bezier": [517, -159, 525, -116, 520, -107, 520, -107]},
        {"line": [520, -107, 519, -92]},
        {"line": [519, -92, 505, -55]},
        {"line": [505, -55, 504, -38]},
        {"line": [504, -38, 502, -36]},
        {"line": [502, -36, 504, -34]},
        {"line": [504, -34, 510, -23]},
        {"line": [510, -23, 516, -19]},
        {"line": [516, -19, 520, -15]},
        {"line": [520, -15, 520, -12]},
        {"line": [520, -12, 512, -8]},
        {"line": [512, -8, 509, -9]},
        {"line": [509, -9, 502, -9]},
        {"line": [502, -9, 498, -8]},
        {"line": [498, -8, 494, -10]},
        {"bezier": [494, -10, 478, -7, 483, -15, 483, -15]},
        {"line": [483, -15, 484, -24]},
        {"line": [484, -24, 482, -36]},
        {"line": [482, -36, 483, -43]},
        {"line": [483, -43, 486, -68]},
        {"line": [486, -68, 484, -93]},
        {"line": [484, -93, 482, -101]},
        {"line": [482, -101, 482, -119]},
        {"line": [482, -119, 486, -129]},
        {"line": [486, -129, 486, -137]},
        {"line": [486, -137, 486, -138]},
        {"line": [486, -138, 482, -155]},
        {"line": [482, -155, 480, -229]},
        {"line": [480, -229, 479, -155]}
    ],

    [
        {"stroke": [0, 0, 0]},
        {"strokeWidth": 1},
        {"line": [438, -450, 437, -423]},
        {"line": [437, -423, 414, -426]},
        {"line": [414, -426, 414, -441]},
        {"line": [414, -441, 438, -450]}
    ],

    [
        {"stroke": [0, 0, 0]},
        {"strokeWidth": 1},
        {"line": [474, -458, 469, -366]},
        {"line": [469, -366, 444, -454]},
        {"line": [444, -454, 474, -458]}
    ],

    [
        {"stroke": [0, 0, 0]},
        {"strokeWidth": 1},
        {"line": [404, -419, 403, -363]},
        {"bezier": [403, -363, 403, -363, 409, -362, 410, -363]},
        {"bezier": [410, -363, 411, -365, 413, -419, 413, -419]},
        {"line": [413, -419, 404, -419]}
    ],

    [
        {"stroke": [0, 0, 0]},
        {"strokeWidth": 1},
        {"line": [423, -417, 417, -417]},
        {"line": [417, -417, 413, -366]},
        {"line": [413, -366, 423, -417]}
    ],

    [
        {"stroke": [0, 0, 0]},
        {"strokeWidth": 1},
        {"bezier": [404, -354, 404, -354, 396, -356, 396, -354]},
        {"bezier": [396, -354, 396, -353, 389, -288, 389, -288]},
        {"line": [389, -288, 397, -291]},
        {"line": [397, -291, 404, -354]}
    ],

    [
        {"stroke": [0, 0, 0]},
        {"strokeWidth": 1},
        {"line": [419, -354, 409, -354]},
        {"line": [409, -354, 400, -292]},
        {"bezier": [400, -292, 400, -292, 414, -321, 414, -323]},
        {"bezier": [414, -323, 414, -326, 419, -354, 419, -354]}
    ],

    [
        {"stroke": [0, 0, 0]},
        {"strokeWidth": 1},
        {"bezier": [472, -304, 472, -304, 431, -303, 431, -302]},
        {"line": [431, -302, 431, -272]},
        {"line": [431, -272, 472, -272]},
        {"line": [472, -272, 472, -304]}
    ],

    [
        {"stroke": [0, 0, 0]},
        {"strokeWidth": 1},
        {"line": [472, -246, 438, -246]},
        {"bezier": [438, -246, 439, -247, 458, -166, 458, -166]},
        {"line": [458, -166, 472, -246]}
    ],

    [
        {"stroke": [0, 0, 0]},
        {"strokeWidth": 1},
        {"line": [468, -119, 451, -119]},
        {"line": [451, -119, 465, -45]},
        {"line": [465, -45, 468, -119]}
    ],

    [
        {"stroke": [0, 0, 0]},
        {"strokeWidth": 1},
        {"line": [486, -458, 491, -366]},
        {"line": [491, -366, 516, -454]},
        {"line": [516, -454, 486, -458]}
    ],

    [
        {"stroke": [0, 0, 0]},
        {"strokeWidth": 1},
        {"line": [522, -450, 524, -423]},
        {"line": [524, -423, 546, -426]},
        {"line": [546, -426, 546, -441]},
        {"line": [546, -441, 522, -450]}
    ],

    [
        {"stroke": [0, 0, 0]},
        {"strokeWidth": 1},
        {"line": [556, -419, 558, -363]},
        {"bezier": [558, -363, 558, -363, 551, -362, 550, -363]},
        {"bezier": [550, -363, 550, -365, 548, -419, 548, -419]},
        {"line": [548, -419, 556, -419]}
    ],

    [
        {"stroke": [0, 0, 0]},
        {"strokeWidth": 1},
        {"line": [537, -417, 544, -417]},
        {"line": [544, -417, 548, -366]},
        {"line": [548, -366, 537, -417]}
    ],

    [
        {"stroke": [0, 0, 0]},
        {"strokeWidth": 1},
        {"bezier": [556, -354, 556, -354, 565, -356, 565, -354]},
        {"bezier": [565, -354, 565, -353, 571, -288, 571, -288]},
        {"line": [571, -288, 564, -291]},
        {"line": [564, -291, 556, -354]}
    ],

    [
        {"stroke": [0, 0, 0]},
        {"strokeWidth": 1},
        {"line": [541, -354, 551, -354]},
        {"line": [551, -354, 560, -292]},
        {"bezier": [560, -292, 560, -292, 546, -321, 546, -323]},
        {"bezier": [546, -323, 546, -326, 541, -354, 541, -354]}
    ],

    [
        {"stroke": [0, 0, 0]},
        {"strokeWidth": 1},
        {"bezier": [488, -304, 488, -304, 529, -303, 529, -302]},
        {"line": [529, -302, 529, -272]},
        {"line": [529, -272, 488, -272]},
        {"line": [488, -272, 488, -304]}
    ],

    [
        {"stroke": [0, 0, 0]},
        {"strokeWidth": 1},
        {"bezier": [488, -246, 488, -246, 523, -246, 522, -246]},
        {"bezier": [522, -246, 521, -247, 503, -166, 503, -166]},
        {"line": [503, -166, 488, -246]}
    ],

    [
        {"stroke": [0, 0, 0]},
        {"strokeWidth": 1},
        {"line": [493, -119, 510, -119]},
        {"line": [510, -119, 495, -45]},
        {"line": [495, -45, 493, -119]}
    ]
]
